cobroswap/__init__.py
cobroswap/client.py
cobroswap/models.py
cobroswap/payment_link.py
cobroswap-0.0.5.dist-info/LICENSE
cobroswap-0.0.5.dist-info/METADATA
cobroswap-0.0.5.dist-info/WHEEL
cobroswap-0.0.5.dist-info/top_level.txt
cobroswap-0.0.5.dist-info/RECORD
