Metadata-Version: 2.1
Name: cobroswap
Version: 0.0.5
Summary: Python wrapper for CobrosWap.
Home-page: https://pypi.org/project/cobroswap/
Author: Alejo Prieto Dávalos
Author-email: alejoprietodavalos@gmail.com
Project-URL: Source, https://github.com/AlejoPrietoDavalos/cobroswap/
Requires-Python: >=3.11
License-File: LICENSE
Requires-Dist: requests >=2.32.0
Requires-Dist: pydantic >=2.8.2
